structlib/__init__.py
structlib/__main__.cp38-win_amd64.pyd
structlib/__main__.py
structlib/champ.cp38-win_amd64.pyd
structlib/geometrie.cp38-win_amd64.pyd
structlib/licence.cp38-win_amd64.pyd
structlib/modele.cp38-win_amd64.pyd
structlib/resol.cp38-win_amd64.pyd
structlib/txtdata.cp38-win_amd64.pyd
structlib/Slosh/Slosh2D.cp38-win_amd64.pyd
structlib/Slosh/__init__.py
structlib/Slosh/constBE.cp38-win_amd64.pyd
structlib/Slosh/test.cp38-win_amd64.pyd
structlib/acier/__init__.py
structlib/acier/fatigue.cp38-win_amd64.pyd
structlib/donnees/__init__.py
structlib/donnees/enveloppe.cp38-win_amd64.pyd
structlib/donnees/evel_test.cp38-win_amd64.pyd
structlib/elements/__init__.py
structlib/elements/cable.cp38-win_amd64.pyd
structlib/elements/poutre2D.cp38-win_amd64.pyd
structlib/gc/__init__.py
structlib/gc/beton.cp38-win_amd64.pyd
structlib/prec/__init__.py
structlib/prec/integrales.cp38-win_amd64.pyd
structlib/prec/poutreav.cp38-win_amd64.pyd
structlib/prec/poutrecont.cp38-win_amd64.pyd
structlib/prec/trace.cp38-win_amd64.pyd
structlib/section/__init__.py
structlib/section/cara.cp38-win_amd64.pyd
structlib/section/integration.cp38-win_amd64.pyd
structlib/section/lois.cp38-win_amd64.pyd
structlib/vent/__init__.py
structlib/vent/dsp.cp38-win_amd64.pyd
structlib/ventspectral/__init__.py
structlib/ventspectral/desmodes.cp38-win_amd64.pyd
structlib/ventspectral/mvent.cp38-win_amd64.pyd
structlib/ventspectral/paraviewexport.cp38-win_amd64.pyd
structlib/ventspectral/vent.cp38-win_amd64.pyd
structlib-0.2.1.dist-info/LICENSE.txt
structlib-0.2.1.dist-info/METADATA
structlib-0.2.1.dist-info/WHEEL
structlib-0.2.1.dist-info/top_level.txt
structlib-0.2.1.dist-info/RECORD
