Metadata-Version: 2.1
Name: structlib
Version: 0.2.1
Summary: Structural and civil engineering library
Home-page: UNKNOWN
Author: Aymeric Perret du Cray
Author-email: apc.internet@pm.me
License: UNKNOWN
Keywords: structural civil engineering prestressed concrete turbulent wind steel
Platform: UNKNOWN
Requires-Python: >=3
Requires-Dist: pandas
Requires-Dist: matplotlib
Requires-Dist: numpy
Requires-Dist: scipy
Requires-Dist: pycryptodome
